pulumi_mongodbatlas/__init__.py
pulumi_mongodbatlas/_inputs.py
pulumi_mongodbatlas/_utilities.py
pulumi_mongodbatlas/access_list_api_key.py
pulumi_mongodbatlas/advanced_cluster.py
pulumi_mongodbatlas/alert_configuration.py
pulumi_mongodbatlas/api_key.py
pulumi_mongodbatlas/api_key_project_assignment.py
pulumi_mongodbatlas/auditing.py
pulumi_mongodbatlas/backup_compliance_policy.py
pulumi_mongodbatlas/cloud_backup_schedule.py
pulumi_mongodbatlas/cloud_backup_snapshot.py
pulumi_mongodbatlas/cloud_backup_snapshot_export_bucket.py
pulumi_mongodbatlas/cloud_backup_snapshot_export_job.py
pulumi_mongodbatlas/cloud_backup_snapshot_restore_job.py
pulumi_mongodbatlas/cloud_provider_access_authorization.py
pulumi_mongodbatlas/cloud_provider_access_setup.py
pulumi_mongodbatlas/cloud_user_org_assignment.py
pulumi_mongodbatlas/cloud_user_project_assignment.py
pulumi_mongodbatlas/cloud_user_team_assignment.py
pulumi_mongodbatlas/cluster.py
pulumi_mongodbatlas/cluster_outage_simulation.py
pulumi_mongodbatlas/custom_db_role.py
pulumi_mongodbatlas/custom_dns_configuration_cluster_aws.py
pulumi_mongodbatlas/database_user.py
pulumi_mongodbatlas/encryption_at_rest.py
pulumi_mongodbatlas/encryption_at_rest_private_endpoint.py
pulumi_mongodbatlas/event_trigger.py
pulumi_mongodbatlas/federated_database_instance.py
pulumi_mongodbatlas/federated_query_limit.py
pulumi_mongodbatlas/federated_settings_identity_provider.py
pulumi_mongodbatlas/federated_settings_org_config.py
pulumi_mongodbatlas/federated_settings_org_role_mapping.py
pulumi_mongodbatlas/flex_cluster.py
pulumi_mongodbatlas/get_access_list_api_key.py
pulumi_mongodbatlas/get_access_list_api_keys.py
pulumi_mongodbatlas/get_advanced_cluster.py
pulumi_mongodbatlas/get_advanced_clusters.py
pulumi_mongodbatlas/get_alert_configuration.py
pulumi_mongodbatlas/get_alert_configurations.py
pulumi_mongodbatlas/get_api_key.py
pulumi_mongodbatlas/get_api_key_project_assignment.py
pulumi_mongodbatlas/get_api_key_project_assignments.py
pulumi_mongodbatlas-4.1.0.dist-info/METADATA
pulumi_mongodbatlas-4.1.0.dist-info/WHEEL
pulumi_mongodbatlas-4.1.0.dist-info/top_level.txt
pulumi_mongodbatlas-4.1.0.dist-info/RECORD
